goodtables/VERSION
goodtables/__init__.py
goodtables/__main__.py
goodtables/cells.py
goodtables/cli.py
goodtables/config.py
goodtables/error.py
goodtables/exceptions.py
goodtables/helpers.py
goodtables/inspector.py
goodtables/registry.py
goodtables/spec.json
goodtables/spec.py
goodtables/validate.py
goodtables/checks/__init__.py
goodtables/checks/blank_header.py
goodtables/checks/blank_row.py
goodtables/checks/constraints_checks.py
goodtables/checks/duplicate_header.py
goodtables/checks/duplicate_row.py
goodtables/checks/enumerable_constraint.py
goodtables/checks/extra_header.py
goodtables/checks/extra_value.py
goodtables/checks/maximum_constraint.py
goodtables/checks/maximum_length_constraint.py
goodtables/checks/minimum_constraint.py
goodtables/checks/minimum_length_constraint.py
goodtables/checks/missing_header.py
goodtables/checks/missing_value.py
goodtables/checks/non_matching_header.py
goodtables/checks/pattern_constraint.py
goodtables/checks/required_constraint.py
goodtables/checks/type_or_format_error.py
goodtables/checks/unique_constraint.py
goodtables/contrib/__init__.py
goodtables/contrib/checks/__init__.py
goodtables/contrib/checks/blacklisted_value.py
goodtables/contrib/checks/custom_constraint.py
goodtables/contrib/checks/deviated_value.py
goodtables/contrib/checks/foreign_key.py
goodtables/contrib/checks/sequential_value.py
goodtables/contrib/checks/truncated_value.py
goodtables/presets/__init__.py
goodtables/presets/datapackage.py
goodtables/presets/nested.py
goodtables/presets/table.py
goodtables/schemas/report.json
tests/contrib/__init__.py
tests/contrib/checks/__init__.py
tests/contrib/checks/test_blacklisted_value.py
tests/contrib/checks/test_custom_constraint.py
tests/contrib/checks/test_deviated_value.py
tests/contrib/checks/test_foreign_key.py
tests/contrib/checks/test_sequential_value.py
tests/contrib/checks/test_truncated_value.py
tests/presets/__init__.py
tests/presets/test_datapackage.py
tests/presets/test_nested.py
goodtables-2.5.4.dist-info/LICENSE.md
goodtables-2.5.4.dist-info/METADATA
goodtables-2.5.4.dist-info/WHEEL
goodtables-2.5.4.dist-info/entry_points.txt
goodtables-2.5.4.dist-info/top_level.txt
goodtables-2.5.4.dist-info/RECORD
