Metadata-Version: 2.1
Name: goodtables
Version: 2.5.4
Summary: Goodtables is a framework to inspect tabular data.
Home-page: https://github.com/frictionlessdata/goodtables
Author: Open Knowledge International
Author-email: info@okfn.org
License: MIT
Keywords: data validation,frictionless data,open data,json schema,json table schema,data package,tabular data package
Platform: UNKNOWN
Classifier: Development Status :: 4 - Beta
Classifier: Environment :: Web Environment
Classifier: Intended Audience :: Developers
Classifier: License :: OSI Approved :: MIT License
Classifier: Operating System :: OS Independent
Classifier: Programming Language :: Python :: 2
Classifier: Programming Language :: Python :: 2.7
Classifier: Programming Language :: Python :: 3
Classifier: Programming Language :: Python :: 3.4
Classifier: Programming Language :: Python :: 3.5
Classifier: Programming Language :: Python :: 3.6
Classifier: Topic :: Internet :: WWW/HTTP :: Dynamic Content
Classifier: Topic :: Software Development :: Libraries :: Python Modules
Requires-Dist: six (>=1.9)
Requires-Dist: click (>=6.6)
Requires-Dist: click-default-group
Requires-Dist: requests (>=2.10)
Requires-Dist: simpleeval (>=0.9)
Requires-Dist: statistics (>=1.0)
Requires-Dist: tabulator (>=1.40)
Requires-Dist: tableschema (>=1.16.4)
Requires-Dist: datapackage (>=1.10)
Provides-Extra: develop
Requires-Dist: mock ; extra == 'develop'
Requires-Dist: pylama ; extra == 'develop'
Requires-Dist: pytest ; extra == 'develop'
Requires-Dist: pytest-cov ; extra == 'develop'
Requires-Dist: pyyaml ; extra == 'develop'
Provides-Extra: ods
Requires-Dist: ezodf (>=0.3) ; extra == 'ods'
Requires-Dist: lxml (>=3.0) ; extra == 'ods'
